{
  "1": "Tuke Pujuuwah, waanum initak egkema pujusan amina untsuagme.",
  "2": "¡Apuh, wi untsuajam nunú antugtukta! ¡Wi amina egakun untsumag nunú antugtukam yainkata!",
  "3": "Tuke Pujuuwah, ame tsagkugkagtugchawaitkuminig, iwakuk batsamaitsuji.",
  "4": "Tujash ame tsagkugkagtau asam, eme anentsa umijam atatme.",
  "5": "Wika Tuke Pujuuwai ashí mina anentaigjai, kajintsan pujajai. Tuja nii anagkagtuawa nunashkam dekaskeapi tajai.",
  "6": "Wika yaakta kuitamin wajupa asag tsawajat tusa, tsawantan dakajama numamtuk mina Apajuíjun dakajai.",
  "7": "Israel aents aidautigmek Tuke Pujuu taatnuji dakastajum; wagki niyai awai anentak, tuja ashí agkanmaetashkam.",
  "8": "Apajuí Israel aents aidaun tudaujinak ashí tsagkujug agkanmitkattawai."
}